{
  "$schema": "https://gansoft.io/schemas/2025-01/report/variable.schema.json",
  "id": "89333801-A2DB-4527-9BD8-51B91D58B53D",
  "group": 1,
  "type": "short",
  "data": {
    "type": "ServiceType"
  },
  "query": {
    "select": {
      "default": "cast((CASE WHEN A.ReceiverId is NOT NULL THEN 3 ELSE (CASE WHEN AFTH.Category IS NULL AND A.MotherId IS NOT NULL THEN 1 WHEN AFTH.Category = 8 THEN 1 WHEN AFTH.Category = 9 THEN 2 ELSE 0 END) END) as smallint)"
    }
  },
  "format": {
    "name": "ServiceTypeFormatter",
    "params": null
  },  
  "description": {
    "en": "Origin of the animal",
    "es": "Origen del animal",
    "pt": "Origem do animal"
  }
}